snakemake_storage_plugin_irods/__init__.py
snakemake_storage_plugin_irods-0.3.1.dist-info/LICENSE
snakemake_storage_plugin_irods-0.3.1.dist-info/METADATA
snakemake_storage_plugin_irods-0.3.1.dist-info/WHEEL
snakemake_storage_plugin_irods-0.3.1.dist-info/RECORD
